flake8_string_format.py
flake8_string_format-0.2.2.dist-info/DESCRIPTION.rst
flake8_string_format-0.2.2.dist-info/METADATA
flake8_string_format-0.2.2.dist-info/RECORD
flake8_string_format-0.2.2.dist-info/WHEEL
flake8_string_format-0.2.2.dist-info/entry_points.txt
flake8_string_format-0.2.2.dist-info/metadata.json
flake8_string_format-0.2.2.dist-info/top_level.txt
