Metadata-Version: 2.0
Name: flake8-string-format
Version: 0.2.2
Summary: string format checker, plugin for flake8
Home-page: https://github.com/xZise/flake8-string-format
Author: Fabian Neundorf
Author-email: CommodoreFabianus@gmx.de
License: MIT License
Keywords: flake8 format
Platform: UNKNOWN
Classifier: Development Status :: 3 - Alpha
Classifier: Environment :: Console
Classifier: Intended Audience :: Developers
Classifier: License :: OSI Approved :: MIT License
Classifier: Operating System :: OS Independent
Classifier: Programming Language :: Python
Classifier: Programming Language :: Python :: 2.7
Classifier: Programming Language :: Python :: 3
Classifier: Topic :: Software Development :: Libraries :: Python Modules
Classifier: Topic :: Software Development :: Quality Assurance
Requires-Dist: flake8
